at_6290/__init__.py
at_6290/message_streamer.py
at_6290/read_latest_message.py
at_6290-0.1.2.dist-info/LICENSE.txt
at_6290-0.1.2.dist-info/METADATA
at_6290-0.1.2.dist-info/WHEEL
at_6290-0.1.2.dist-info/top_level.txt
at_6290-0.1.2.dist-info/RECORD
